{
  "$schema": "https://developer.microsoft.com/json-schemas/fabric/item/report/definition/visualContainer/2.8.0/schema.json",
  "name": "a1d5084e4f564912bef5",
  "position": {
    "x": 0.61855670103092786,
    "y": 0,
    "z": 0,
    "height": 720,
    "width": 47.010309278350512,
    "tabOrder": 0
  },
  "visual": {
    "visualType": "shape",
    "objects": {
      "shape": [
        {
          "properties": {
            "roundEdge": {
              "expr": {
                "Literal": {
                  "Value": "5L"
                }
              }
            }
          }
        }
      ],
      "fill": [
        {
          "properties": {
            "show": {
              "expr": {
                "Literal": {
                  "Value": "true"
                }
              }
            },
            "fillColor": {
              "solid": {
                "color": {
                  "expr": {
                    "Literal": {
                      "Value": "'#0F5F73'"
                    }
                  }
                }
              }
            }
          }
        },
        {
          "properties": {
            "fillColor": {
              "solid": {
                "color": {
                  "expr": {
                    "ThemeDataColor": {
                      "ColorId": 7,
                      "Percent": -0.5
                    }
                  }
                }
              }
            },
            "transparency": {
              "expr": {
                "Literal": {
                  "Value": "49D"
                }
              }
            }
          },
          "selector": {
            "id": "default"
          }
        }
      ],
      "outline": [
        {
          "properties": {
            "show": {
              "expr": {
                "Literal": {
                  "Value": "false"
                }
              }
            }
          }
        }
      ]
    },
    "visualContainerObjects": {
      "visualLink": [
        {
          "properties": {
            "show": {
              "expr": {
                "Literal": {
                  "Value": "false"
                }
              }
            },
            "type": {
              "expr": {
                "Literal": {
                  "Value": "'PageNavigation'"
                }
              }
            },
            "navigationSection": {
              "expr": {
                "Literal": {
                  "Value": "'dc6b480ee3a61d61a201'"
                }
              }
            }
          }
        }
      ],
      "title": [
        {
          "properties": {
            "titleWrap": {
              "expr": {
                "Literal": {
                  "Value": "true"
                }
              }
            }
          }
        }
      ],
      "background": [
        {
          "properties": {
            "show": {
              "expr": {
                "Literal": {
                  "Value": "false"
                }
              }
            },
            "transparency": {
              "expr": {
                "Literal": {
                  "Value": "0D"
                }
              }
            }
          }
        }
      ],
      "general": [
        {
          "properties": {
            "keepLayerOrder": {
              "expr": {
                "Literal": {
                  "Value": "true"
                }
              }
            }
          }
        }
      ],
      "border": [
        {
          "properties": {
            "width": {
              "expr": {
                "Literal": {
                  "Value": "1D"
                }
              }
            }
          }
        }
      ],
      "visualHeader": [
        {
          "properties": {
            "show": {
              "expr": {
                "Literal": {
                  "Value": "false"
                }
              }
            }
          }
        }
      ]
    },
    "drillFilterOtherVisuals": true
  }
}